gptbots/__init__.py
gptbots/gptbots.py
gptbots-0.1.14.dist-info/LICENSE
gptbots-0.1.14.dist-info/METADATA
gptbots-0.1.14.dist-info/WHEEL
gptbots-0.1.14.dist-info/top_level.txt
gptbots-0.1.14.dist-info/RECORD
