Metadata-Version: 2.1
Name: gptbots
Version: 0.1.14
Summary: A simple Python package for creating and interacting with GPT-based chatbots
Author-email: Carl Vincent Escobar <cvescobar112@protonmail.com>
Keywords: openai,gpt,chatbots
Classifier: Programming Language :: Python :: 3
Classifier: License :: OSI Approved :: MIT License
Classifier: Operating System :: OS Independent
Requires-Python: >=3.8
License-File: LICENSE
Requires-Dist: openai
